anyser/__init__.py
anyser/abc.py
anyser/core.py
anyser/err.py
anyser/g.py
anyser/impls/__init__.py
anyser/impls/bencode.py
anyser/impls/bson.py
anyser/impls/json.py
anyser/impls/json5.py
anyser/impls/pickle.py
anyser/impls/toml.py
anyser/impls/xml.py
anyser/impls/yaml.py
anyser-0.2.0.dist-info/LICENSE
anyser-0.2.0.dist-info/METADATA
anyser-0.2.0.dist-info/WHEEL
anyser-0.2.0.dist-info/top_level.txt
anyser-0.2.0.dist-info/RECORD
