Metadata-Version: 2.1
Name: anyser
Version: 0.2.0
Summary: UNKNOWN
Home-page: https://github.com/Cologler/anyser-python
License: MIT License
Platform: UNKNOWN
Classifier: Development Status :: 5 - Production/Stable
Classifier: License :: OSI Approved :: MIT License
Classifier: Programming Language :: Python :: 3.7
Classifier: Programming Language :: Python :: 3.8
Provides-Extra: bencode
Requires-Dist: bencode.py ; extra == 'bencode'
Provides-Extra: bson
Requires-Dist: bson ; extra == 'bson'
Provides-Extra: json5
Requires-Dist: json5 ; extra == 'json5'
Provides-Extra: toml
Requires-Dist: toml ; extra == 'toml'
Provides-Extra: yaml
Requires-Dist: pyyaml ; extra == 'yaml'
